hdl/fgpa/rest.v

module non_rest #(parameter n=16, s=16) (output wire [s-1:0] QUOTIENT, REMAINDER, output wire done,
    input wire [n-1:0] x, y, input wire clk, reset, start);
    
    reg [s-1:0] Q, R, M;
    integer count;
    reg finish_tk;

    assign QUOTIENT = Q;
    assign REMAINDER = R;
    assign done = finish_tk;

    always @(posedge clk, posedge reset) 
		begin
			if (reset) 
				begin 
					count = 0; finish_tk = 1'b0; Q = 0; R = 0; 
				end
			else if (start) 
				begin 
					Q = x; M = y; count = 1; 
				end 
			else if (count > 0) 
				begin 
					if (R[s-1] == 1) 
						begin  
							R = R << 1;             
							R[0] = Q[s-1];          
							Q = Q << 1;             
							R = R + M; 
						end
					else 
						begin    
							R = R << 1;           
							R[0] = Q[s-1];        
							Q = Q << 1;           
							R = R - M;  
						end
			if (R[s-1] == 1) 
				begin 
					Q[0] = 0; 
				end 
			else 
				begin 
					Q[0] = 1; 
				end             
			 count = count + 1; 
			 if (count==s+1) 
    begin 
		count = 0;
		if (R[s-1] == 1) 
			begin 
				R = R + M; 
			end  
		finish_tk = 1'b1;
	end
	end
    end
endmodule

hdl/fgpa/rest_tb.v
module non_res_test;

    reg clk, reset;
    reg [15:0] x, y;
    wire [15:0] q, r;
    reg start; 
    wire done_tick;
    wire tx_full1, rx_empty1, tx_full2, rx_empty2;

    localparam c_CLOCK_PERIOD_NS=20; 
    initial begin clk=0; reset=0; forever #c_CLOCK_PERIOD_NS clk=~clk; end
    
    non_rest rest(.QUOTIENT(q), .REMAINDER(r), .done(done_tick), .x(x), .y(y), .clk(clk), .reset(reset), .start(start));
    initial begin 
        #80;
        reset = 1'b1; 
        #200;
        reset = 1'b0;
        #80; 
        {x, y} = {16'b0000000000000011, 16'b0000000000001000};  
        @(posedge clk) start = 1'b1; 
	#20;
        @(posedge clk) start = 1'b0;
        #600;
        $finish;
    end
initial begin
			if(x>y) $monitor("At time = %t,Q = %b, R = %b", $time, q, r);
			else $monitor("At time = %t,Q = %b, R = %b", $time, r, q);
			end

    initial begin
        $dumpfile("a.vcd");
        $dumpvars;
    end

endmodule

hdl/fgpa/a.vcd
$date
	Fri May  3 03:32:32 2019
$end
$version
	Icarus Verilog
$end
$timescale
	1s
$end
$scope module non_res_test $end
$var wire 1 ! done_tick $end
$var wire 16 " q [15:0] $end
$var wire 16 # r [15:0] $end
$var reg 1 $ clk $end
$var reg 1 % reset $end
$var reg 1 & start $end
$var reg 16 ' x [15:0] $end
$var reg 16 ( y [15:0] $end
$scope module rest $end
$var wire 16 ) QUOTIENT [15:0] $end
$var wire 16 * REMAINDER [15:0] $end
$var wire 1 + clk $end
$var wire 1 ! done $end
$var wire 1 , reset $end
$var wire 1 - start $end
$var wire 16 . x [15:0] $end
$var wire 16 / y [15:0] $end
$var reg 16 0 M [15:0] $end
$var reg 16 1 Q [15:0] $end
$var reg 16 2 R [15:0] $end
$var integer 32 3 count [31:0] $end
$var reg 1 4 finish_tk $end
$upscope $end
$upscope $end
$enddefinitions $end
#0
$dumpvars
x4
bx 3
bx 2
bx 1
bx 0
bx /
bx .
x-
0,
0+
bx *
bx )
bx (
bx '
x&
0%
0$
bx #
bx "
x!
$end
#20
1$
1+
#40
0$
0+
#60
1$
1+
#80
b0 2
b0 #
b0 *
b0 1
b0 "
b0 )
04
0!
b0 3
0$
0+
1%
1,
#100
1$
1+
#120
0$
0+
#140
1$
1+
#160
0$
0+
#180
1$
1+
#200
0$
0+
#220
1$
1+
#240
0$
0+
#260
1$
1+
#280
0$
0+
0%
0,
#300
1$
1+
#320
0$
0+
#340
1$
1+
#360
0$
0+
b11 '
b11 .
b1000 (
b1000 /
#380
b1 3
b1000 0
b11 1
b11 "
b11 )
1&
1-
1$
1+
#400
0$
0+
#420
b10 3
b1111111111111000 #
b1111111111111000 *
b110 1
b110 "
b110 )
b1111111111111000 2
0&
0-
1$
1+
#440
0$
0+
#460
b11 3
b1100 1
b1100 "
b1100 )
b1111111111111000 2
b1111111111111000 #
b1111111111111000 *
1$
1+
#480
0$
0+
#500
b100 3
b11000 1
b11000 "
b11000 )
b1111111111111000 2
b1111111111111000 #
b1111111111111000 *
1$
1+
#520
0$
0+
#540
b101 3
b110000 1
b110000 "
b110000 )
b1111111111111000 2
b1111111111111000 #
b1111111111111000 *
1$
1+
#560
0$
0+
#580
b110 3
b1100000 1
b1100000 "
b1100000 )
b1111111111111000 2
b1111111111111000 #
b1111111111111000 *
1$
1+
#600
0$
0+
#620
b111 3
b11000000 1
b11000000 "
b11000000 )
b1111111111111000 2
b1111111111111000 #
b1111111111111000 *
1$
1+
#640
0$
0+
#660
b1000 3
b110000000 1
b110000000 "
b110000000 )
b1111111111111000 2
b1111111111111000 #
b1111111111111000 *
1$
1+
#680
0$
0+
#700
b1001 3
b1100000000 1
b1100000000 "
b1100000000 )
b1111111111111000 2
b1111111111111000 #
b1111111111111000 *
1$
1+
#720
0$
0+
#740
b1010 3
b11000000000 1
b11000000000 "
b11000000000 )
b1111111111111000 2
b1111111111111000 #
b1111111111111000 *
1$
1+
#760
0$
0+
#780
b1011 3
b110000000000 1
b110000000000 "
b110000000000 )
b1111111111111000 2
b1111111111111000 #
b1111111111111000 *
1$
1+
#800
0$
0+
#820
b1100 3
b1100000000000 1
b1100000000000 "
b1100000000000 )
b1111111111111000 2
b1111111111111000 #
b1111111111111000 *
1$
1+
#840
0$
0+
#860
b1101 3
b11000000000000 1
b11000000000000 "
b11000000000000 )
b1111111111111000 2
b1111111111111000 #
b1111111111111000 *
1$
1+
#880
0$
0+
#900
b1110 3
b110000000000000 1
b110000000000000 "
b110000000000000 )
b1111111111111000 2
b1111111111111000 #
b1111111111111000 *
1$
1+
#920
0$
0+
#940
b1111 3
b1100000000000000 1
b1100000000000000 "
b1100000000000000 )
b1111111111111000 2
b1111111111111000 #
b1111111111111000 *
1$
1+
#960
0$
0+
#980
b10000 3
b1000000000000000 1
b1000000000000000 "
b1000000000000000 )
b1111111111111001 2
b1111111111111001 #
b1111111111111001 *
1$
1+
#1000
0$
0+
#1020
14
1!
b0 3
b0 1
b0 "
b0 )
b11 2
b11 #
b11 *
1$
1+
