hdl/nerd.v

module rd #(parameter n=8, p=8) (output wire [p-1:0] quotient, remainder, output wire done,
    input wire [n-1:0] x, y, input wire clk, reset, start);
    reg [p-1:0] q, r, rnext;
    integer z1, z2, count;
    reg qbit, done_tick;

    assign quotient = q;
    assign remainder = r;
    assign done = done_tick;

    always @(posedge clk, posedge reset) begin
      if (reset) begin count = 0; done_tick = 1'b0; qbit = 1'b0; q = 0; r = 0; end
      else if (start) begin rnext = x; count = 1; end
      else if (count>0) begin
				//both are run at a time in always to make it in one clock cycle
        r = rnext;
        qbit = 1'b0;
        z1 = 2*r - y;
        z2 = 2*r + y;//first bit iteration
        if (r[p-1]==1) begin rnext = z2; end
        if (r[p-1]==0) begin rnext = z1; end
        if (rnext[p-1]==1) begin qbit = 1'b0; end
        if (rnext[p-1]==0) begin qbit = 1'b1; end
        q = {q[p-2:0], qbit};


        r = rnext;
        qbit = 1'b0;
        z1 = 2*r - y;//second bit iteration and then it again repeats
        z2 = 2*r + y;
        if (r[p-1]==1) begin rnext = z2; end
        if (r[p-1]==0) begin rnext = z1; end
        if (rnext[p-1]==1) begin qbit = 1'b0; end
        if (rnext[p-1]==0) begin qbit = 1'b1; end
        q = {q[p-2:0], qbit};

        count = count + 1;
        if (count==p-3) begin
          count=0;
          done_tick = 1'b1;
        if (r[p-1]==1) begin r = r + y; end
        end
      end
    end
endmodule

hdl/nerd_tb.v


module rd_test;

    reg clk, reset;
    reg [7:0] x, y;
    wire [7:0] q, r;
    reg start; 
    wire done_tick;
    wire tx_full1, rx_empty1, tx_full2, rx_empty2;

    localparam c_CLOCK_PERIOD_NS=20; 
    initial begin clk=0; reset=0; forever #c_CLOCK_PERIOD_NS clk=~clk; end
    
    rd rd1 (.quotient(q), .remainder(r), .done(done_tick), .x(x), .y(y), .clk(clk), .reset(reset), .start(start));
    initial begin 
        #80;
        reset = 1'b1;
        #200;
        reset = 1'b0;
        #200; //wait for 5 clks
        {x, y, start} = {8'b00000011, 8'b00001000, 1'b1};
        @(posedge clk) start = 1'b1; //generate only a pulse
        @(posedge clk) start = 1'b0; //generate only a pulse
        #100000;

        //above can be put in a loop to transmit more data.
        $finish;
    end
    initial begin
        $dumpfile("a.vcd");
        $dumpvars;
    end
endmodule

hdl/a.vcd
$date
	Fri May  3 11:00:17 2019
$end
$version
	Icarus Verilog
$end
$timescale
	1s
$end
$scope module rd_test $end
$var wire 1 ! done_tick $end
$var wire 8 " q [7:0] $end
$var wire 8 # r [7:0] $end
$var reg 1 $ clk $end
$var reg 1 % reset $end
$var reg 1 & start $end
$var reg 8 ' x [7:0] $end
$var reg 8 ( y [7:0] $end
$scope module rd1 $end
$var wire 1 ) clk $end
$var wire 1 ! done $end
$var wire 8 * quotient [7:0] $end
$var wire 8 + remainder [7:0] $end
$var wire 1 , reset $end
$var wire 1 - start $end
$var wire 8 . x [7:0] $end
$var wire 8 / y [7:0] $end
$var integer 32 0 count [31:0] $end
$var reg 1 1 done_tick $end
$var reg 8 2 q [7:0] $end
$var reg 1 3 qbit $end
$var reg 8 4 r [7:0] $end
$var reg 8 5 rnext [7:0] $end
$var integer 32 6 z1 [31:0] $end
$var integer 32 7 z2 [31:0] $end
$upscope $end
$upscope $end
$enddefinitions $end
#0
$dumpvars
bx 7
bx 6
bx 5
bx 4
x3
bx 2
x1
bx 0
bx /
bx .
x-
0,
bx +
bx *
0)
bx (
bx '
x&
0%
0$
bx #
bx "
x!
$end
#20
1$
1)
#40
0$
0)
#60
1$
1)
#80
b0 4
b0 #
b0 +
b0 2
b0 "
b0 *
03
01
0!
b0 0
0$
0)
1%
1,
#100
1$
1)
#120
0$
0)
#140
1$
1)
#160
0$
0)
#180
1$
1)
#200
0$
0)
#220
1$
1)
#240
0$
0)
#260
1$
1)
#280
0$
0)
0%
0,
#300
1$
1)
#320
0$
0)
#340
1$
1)
#360
0$
0)
#380
1$
1)
#400
0$
0)
#420
1$
1)
#440
0$
0)
#460
1$
1)
#480
0$
0)
b11 '
b11 .
b1000 (
b1000 /
1&
1-
#500
b1 0
b11 5
1$
1)
#520
0$
0)
#540
b10 0
b1 2
b1 "
b1 *
13
b100 5
b1000000100 7
b111110100 6
b11111110 4
b11111110 #
b11111110 +
0&
0-
1$
1)
#560
0$
0)
#580
b11 0
b110 2
b110 "
b110 *
b11111000 5
b1000 7
b11111111111111111111111111111000 6
03
b0 4
b0 #
b0 +
1$
1)
#600
0$
0)
#620
b100 0
b11000 2
b11000 "
b11000 *
b111111000 7
b111101000 6
b11111000 4
b11111000 #
b11111000 +
1$
1)
#640
0$
0)
#660
b0 4
b0 #
b0 +
11
1!
b0 0
b1100000 2
b1100000 "
b1100000 *
1$
1)
